stn/__init__.py
stn/transformer.py
stn-1.0.1.dist-info/METADATA
stn-1.0.1.dist-info/RECORD
stn-1.0.1.dist-info/WHEEL
stn-1.0.1.dist-info/top_level.txt
